medlitanno/__init__.py
medlitanno/__main__.py
medlitanno/cli.py
medlitanno/annotation/__init__.py
medlitanno/annotation/batch_processor.py
medlitanno/annotation/converter.py
medlitanno/annotation/core.py
medlitanno/annotation/monitor.py
medlitanno/annotation/position_matcher.py
medlitanno/common/__init__.py
medlitanno/common/base.py
medlitanno/common/exceptions.py
medlitanno/common/llm_client.py
medlitanno/common/utils.py
medlitanno/config/defaults.json
medlitanno/data/opengwas.csv
medlitanno/mragent/__init__.py
medlitanno/mragent/core/LLM.py
medlitanno/mragent/core/__init__.py
medlitanno/mragent/core/agent_tool.py
medlitanno/mragent/core/agent_workflow.py
medlitanno/mragent/core/agent_workflow_OE.py
medlitanno/mragent/core/template_text.py
medlitanno/pubmed/__init__.py
medlitanno/pubmed/integration.py
medlitanno/pubmed/searcher.py
medlitanno/templates/annotation_prompt.txt
medlitanno-1.1.1.dist-info/licenses/LICENSE
medlitanno-1.1.1.dist-info/METADATA
medlitanno-1.1.1.dist-info/WHEEL
medlitanno-1.1.1.dist-info/entry_points.txt
medlitanno-1.1.1.dist-info/top_level.txt
medlitanno-1.1.1.dist-info/RECORD
