Metadata-Version: 2.4
Name: medlitanno
Version: 1.1.1
Summary: Medical Literature Analysis and Annotation System with LLM-powered automation
Home-page: https://github.com/chenxingqiang/medlitanno
Author: Chen Xingqiang
Author-email: Chen Xingqiang <chenxingqiang@gmail.com>
License: MIT
Project-URL: Homepage, https://github.com/chenxingqiang/medlitanno
Project-URL: Bug Tracker, https://github.com/chenxingqiang/medlitanno/issues
Project-URL: Documentation, https://github.com/chenxingqiang/medlitanno/blob/main/docs/
Project-URL: Source Code, https://github.com/chenxingqiang/medlitanno
Keywords: medical literature,annotation,pubmed search,mendelian randomization,llm,biomedical nlp,causal inference,gwas,automation,literature mining
Classifier: Development Status :: 4 - Beta
Classifier: Intended Audience :: Science/Research
Classifier: Intended Audience :: Healthcare Industry
Classifier: License :: OSI Approved :: MIT License
Classifier: Operating System :: OS Independent
Classifier: Programming Language :: Python :: 3
Classifier: Programming Language :: Python :: 3.9
Classifier: Programming Language :: Python :: 3.10
Classifier: Programming Language :: Python :: 3.11
Classifier: Programming Language :: Python :: 3.12
Classifier: Topic :: Scientific/Engineering :: Bio-Informatics
Classifier: Topic :: Scientific/Engineering :: Medical Science Apps.
Classifier: Topic :: Text Processing :: Linguistic
Requires-Python: >=3.9
License-File: LICENSE
Dynamic: author
Dynamic: home-page
Dynamic: license-file
Dynamic: requires-python
